{
  "$schema": "https://docs.renovatebot.com/renovate-schema.json",
  "extends": [
    "config:recommended",
    "group:allNonMajor",
    "schedule:earlyMondays",
    "schedule:automergeNonOfficeHours"
  ],
  "timezone": "Europe/Berlin",
  "labels": [
    "dependencies",
    "no milestone"
  ],
  "prHourlyLimit": 10,
  "packageRules": [
    {
      "matchManagers": [
        "npm"
      ],
      "ignorePaths": [
        "odata-connector/cap-bookshop/**"
      ],
      "enabled": false
    },
    // Don't update dockerfile so it never points to a valid connector version
    // This way it always has to be manually specified
    {
      "matchManagers": [
        "dockerfile"
      ],
      "ignorePaths": [
        "odata-connector/Dockerfile"
      ],
      "enabled": false
    },
    {
      "matchManagers": [
        "maven",
        "dockerfile"
      ],
      "matchUpdateTypes": [
        "minor",
        "patch",
        "pin",
        "digest"
      ],
      "automerge": true
    },

    {
      "matchManagers": [
        "github-actions"
      ],
      "automerge": true
    },
    {
      "matchBaseBranches": [
        "release/*"
      ],
      "matchUpdateTypes": [
        "major"
      ],
      "enabled": false
    },
    {
      "matchBaseBranches": [
        "release/*"
      ],
      "matchPackageNames": [
        "io.camunda*"
      ],
      "matchUpdateTypes": [
        "major",
        "minor",
        "replacement"
      ],
      "enabled": false
    },
    {
      "matchPackageNames": [
        "camunda/infra-global-github-actions"
      ],
      "matchUpdateTypes": [
        "digest"
      ],
      "changelogUrl": "https://github.com/camunda/infra-global-github-actions/compare/{{currentDigest}}..{{newDigest}}"
    }
  ],
  "baseBranchPatterns": [
    "main",
    "/^release\\/.*/"
  ]
}